patchme-0.1.1.dist-info/DESCRIPTION.rst
patchme-0.1.1.dist-info/METADATA
patchme-0.1.1.dist-info/RECORD
patchme-0.1.1.dist-info/WHEEL
patchme-0.1.1.dist-info/metadata.json
patchme-0.1.1.dist-info/top_level.txt
src/patchme/__init__.py
